Metadata-Version: 2.1
Name: brave-bookmarks
Version: 1.1.1
Home-page: https://github.com/talwrii/brave-bookmarks
Author: @readwithai
Author-email: talwrii@gmail.com
License: MIT
Keywords: bookmarks,brave,command-line
License-File: LICENSE
